{"1":{"id":1,"define":"-","title":"dialog error","message":"idもdefineも見つかりませんでした","dialog_type":1,"label_yes":"-","label_no":"-"},"2":{"id":2,"define":"MSG_CAVE_CLEAR","title":"クリア！","message":"クリアしました！最初から始めます","dialog_type":1,"label_yes":"-","label_no":"-"},"3":{"id":3,"define":"MSG_GAME_OVER","title":"GAME OVER","message":"全滅しました<br/>最初から始めます","dialog_type":1,"label_yes":"-","label_no":"-"},"4":{"id":4,"define":"MSG_NEXT_FLOOR_CONFIRM","title":"階段を発見","message":"階段を発見しました。<br/>次の階へ進みますか？","dialog_type":2,"label_yes":"-","label_no":"-"},"5":{"id":5,"define":"MSG_TEST","title":"<%= test_title %>","message":"<%= test_msg %>","dialog_type":2,"label_yes":"-","label_no":"-"},"6":{"id":6,"define":"MSG_TEST","title":"<%= test_title %>","message":"<%= test_msg %>","dialog_type":2,"label_yes":"-","label_no":"-"},"10001":{"id":10001,"define":"-","title":"プレイヤーが見つかりません","message":"該当のプレイヤーは見つかりませんでした。","dialog_type":1,"label_yes":"-","label_no":"-"},"10002":{"id":10002,"define":"-","title":"error","message":"カードデータが見つかりません","dialog_type":1,"label_yes":"-","label_no":"-"},"10003":{"id":10003,"define":"-","title":"error","message":"エラーメッセージデータが見つかりません","dialog_type":1,"label_yes":"-","label_no":"-"},"10004":{"id":10004,"define":"-","title":"error","message":"指定のカードがありません","dialog_type":1,"label_yes":"-","label_no":"-"}}