{"1001":{"id":1001,"world_id":1,"area_id":1,"map_pos_x":63,"map_pos_y":88,"icon_id":[1,2,3,0,0,0,0,0,0,0,0],"icon_x":[60,170,240,0,0,0,0,0,0,0,0],"icon_y":[80,50,100,0,0,0,0,0,0,0,0]},"1002":{"id":1002,"world_id":1,"area_id":2,"map_pos_x":127,"map_pos_y":60,"icon_id":[1,2,3,0,0,0,0,0,0,0,0],"icon_x":[60,170,240,0,0,0,0,0,0,0,0],"icon_y":[80,50,100,0,0,0,0,0,0,0,0]},"1003":{"id":1003,"world_id":1,"area_id":3,"map_pos_x":168,"map_pos_y":108,"icon_id":[1,2,3,0,0,0,0,0,0,0,0],"icon_x":[60,170,240,0,0,0,0,0,0,0,0],"icon_y":[80,50,100,0,0,0,0,0,0,0,0]},"2001":{"id":2001,"world_id":2,"area_id":1,"map_pos_x":1,"map_pos_y":1,"icon_id":[1,0,0,0,0,0,0,0,0,0,0],"icon_x":[1,0,0,0,0,0,0,0,0,0,0],"icon_y":[1,0,0,0,0,0,0,0,0,0,0]},"101001":{"id":101001,"world_id":101,"area_id":1,"map_pos_x":1,"map_pos_y":1,"icon_id":[1,0,0,0,0,0,0,0,0,0,0],"icon_x":[1,0,0,0,0,0,0,0,0,0,0],"icon_y":[1,0,0,0,0,0,0,0,0,0,0]},"101002":{"id":101002,"world_id":101,"area_id":2,"map_pos_x":1,"map_pos_y":1,"icon_id":[1,0,0,0,0,0,0,0,0,0,0],"icon_x":[1,0,0,0,0,0,0,0,0,0,0],"icon_y":[1,0,0,0,0,0,0,0,0,0,0]}}